flake8_peewee.py
flake8_peewee-0.1.0.dist-info/LICENSE
flake8_peewee-0.1.0.dist-info/METADATA
flake8_peewee-0.1.0.dist-info/WHEEL
flake8_peewee-0.1.0.dist-info/entry_points.txt
flake8_peewee-0.1.0.dist-info/top_level.txt
flake8_peewee-0.1.0.dist-info/RECORD
