Metadata-Version: 2.1
Name: flake8-peewee
Version: 0.1.0
Summary: flake8 plugin which checks for peewee usage syntax error
Home-page: https://github.com/Zioyi/flake8-peewee
Author: Zioyi
Author-email: newsunstudy@163.com
License: MIT
Platform: UNKNOWN
Classifier: License :: OSI Approved :: MIT License
Classifier: Programming Language :: Python :: 3
Classifier: Programming Language :: Python :: 3 :: Only
Classifier: Programming Language :: Python :: 3.6
Classifier: Programming Language :: Python :: 3.7
Classifier: Programming Language :: Python :: 3.8
Requires-Python: >=3.6.1
Requires-Dist: flake8 (>=3.7)
Requires-Dist: importlib-metadata (>=0.9) ; python_version < "3.8"
